cwa_qr/__init__.py
cwa_qr/cwa.py
cwa_qr/cwa_pb2.py
cwa_qr/poster.py
cwa_qr/rollover.py
cwa_qr/seed.py
cwa_qr/test_cwa.py
cwa_qr/test_poster.py
cwa_qr/test_rollover.py
cwa_qr/test_seed.py
cwa_qr-1.2.2.dist-info/LICENSE.txt
cwa_qr-1.2.2.dist-info/METADATA
cwa_qr-1.2.2.dist-info/WHEEL
cwa_qr-1.2.2.dist-info/top_level.txt
cwa_qr-1.2.2.dist-info/zip-safe
cwa_qr-1.2.2.dist-info/RECORD
