Metadata-Version: 2.1
Name: cwa-qr
Version: 1.2.2
Summary: Python Implementation of the CoronaWarnApp (CWA) Event Registration
Home-page: https://github.com/MaZderMind/cwa-qr
Author: Peter Körner
Author-email: peter@mazdermind.de
Project-URL: Bug Tracker, https://github.com/MaZderMind/cwa-qr/issues
Classifier: Programming Language :: Python :: 3
Classifier: License :: OSI Approved :: MIT License
Classifier: Operating System :: OS Independent
Classifier: Development Status :: 5 - Production/Stable
License-File: LICENSE.txt
Requires-Dist: Pillow
Requires-Dist: protobuf
Requires-Dist: qrcode
Requires-Dist: six (>=1.15.0)
Requires-Dist: svgutils
